README.md
setup.py
runninglight/__init__.py
runninglight.egg-info/PKG-INFO
runninglight.egg-info/SOURCES.txt
runninglight.egg-info/dependency_links.txt
runninglight.egg-info/top_level.txt