Metadata-Version: 2.1
Name: runninglight
Version: 0.1.0
Summary: Package for controlling an LED running light that is hooked up to a Raspberry Pi
Home-page: https://github.com/TimHanewich/RunningLightControl
Author: Tim Hanewich
Author-email: tahanewich@live.com
License: UNKNOWN
Platform: UNKNOWN
Classifier: Programming Language :: Python :: 3
Classifier: License :: OSI Approved :: MIT License
Classifier: Operating System :: OS Independent
Requires-Python: >=3.6
